[
	{
		"sha": "d80c7613",
		"authored_at": "2024-02-01T10:02:00.000Z",
		"message": "Improve performance of SessionPanel",
		"files": ["vite.config.ts"]
	},
	{
		"sha": "2f413c4a",
		"authored_at": "2024-02-01T10:06:00.000Z",
		"message": "Refactor SessionPanel for clarity",
		"files": [
			"vite.config.ts",
			"src/services/storage.ts",
			"tests/integration.test.ts",
			"src/types/Link.ts",
			"src/components/Modal.tsx"
		]
	},
	{
		"sha": "1b53d83c",
		"authored_at": "2024-02-01T10:10:00.000Z",
		"message": "Remove deprecated Panel",
		"files": ["src/utils/parse.ts", "package.json"]
	},
	{
		"sha": "b8693071",
		"authored_at": "2024-02-01T10:16:00.000Z",
		"message": "Fix memory leak in SessionPanel",
		"files": [
			"src/hooks/useData.ts",
			"tests/hooks.test.ts",
			"vite.config.ts",
			"README.md"
		]
	},
	{
		"sha": "cede1717",
		"authored_at": "2024-02-01T10:22:00.000Z",
		"message": "Update Button to use new API",
		"files": ["tests/integration.test.ts"]
	},
	{
		"sha": "92c2dd2e",
		"authored_at": "2024-02-01T10:25:00.000Z",
		"message": "Improve performance of Timeline",
		"files": ["vite.config.ts", "src/utils/validate.ts"]
	},
	{
		"sha": "5a42f5cb",
		"authored_at": "2024-02-01T10:32:00.000Z",
		"message": "Update useData to use new API",
		"files": [
			"package.json",
			"src/components/Modal.tsx",
			"src/utils/format.ts",
			"tests/hooks.test.ts"
		]
	},
	{
		"sha": "032d74a2",
		"authored_at": "2024-02-01T10:36:00.000Z",
		"message": "Refactor Timeline for clarity",
		"files": [
			"src/types/User.ts",
			"vite.config.ts",
			"tests/utils.test.ts",
			"package.json"
		]
	},
	{
		"sha": "ac4db04e",
		"authored_at": "2024-02-01T10:41:00.000Z",
		"message": "Add tests for Timeline",
		"files": [
			"src/hooks/useBadge.ts",
			"tests/utils.test.ts",
			"src/hooks/useForm.ts"
		]
	},
	{
		"sha": "95171add",
		"authored_at": "2024-02-01T10:47:00.000Z",
		"message": "Remove deprecated Dialog",
		"files": ["src/types/Commit.ts", "package.json"]
	},
	{
		"sha": "b0955e4a",
		"authored_at": "2024-02-01T10:50:00.000Z",
		"message": "Add Dialog component",
		"files": [
			"package.json",
			"tests/utils.test.ts",
			"src/utils/parse.ts",
			"tests/components.test.ts",
			"src/services/storage.ts"
		]
	},
	{
		"sha": "6a0c5ff5",
		"authored_at": "2024-02-01T10:55:00.000Z",
		"message": "Fix race condition in useData",
		"files": [
			"src/types/Repo.ts",
			"tests/integration.test.ts",
			"src/services/auth.ts",
			"src/services/cache.ts",
			"src/utils/format.ts"
		]
	},
	{
		"sha": "7c71dd6c",
		"authored_at": "2024-02-01T11:01:00.000Z",
		"message": "Update SessionPanel to use new API",
		"files": [
			"vite.config.ts",
			"src/components/Badge.tsx",
			"src/components/Input.tsx"
		]
	},
	{
		"sha": "c35233c9",
		"authored_at": "2024-02-01T11:06:00.000Z",
		"message": "Add Modal component",
		"files": ["vite.config.ts", "README.md", "package.json"]
	},
	{
		"sha": "1eff0222",
		"authored_at": "2024-02-01T11:11:00.000Z",
		"message": "Add Modal component",
		"files": [
			"tests/components.test.ts",
			"src/types/Session.ts",
			"src/components/Dialog.tsx",
			"src/types/Commit.ts"
		]
	},
	{
		"sha": "8f05a674",
		"authored_at": "2024-02-01T11:17:00.000Z",
		"message": "Add type definitions for Timeline",
		"files": [
			"vite.config.ts",
			"src/hooks/useAuth.ts",
			"README.md",
			"package.json"
		]
	},
	{
		"sha": "c3f58990",
		"authored_at": "2024-02-01T11:21:00.000Z",
		"message": "Add tests for Timeline",
		"files": [
			"src/utils/parse.ts",
			"src/types/Session.ts",
			"tests/hooks.test.ts",
			"vite.config.ts",
			"src/hooks/useData.ts"
		]
	},
	{
		"sha": "a4cf5029",
		"authored_at": "2024-02-01T11:27:00.000Z",
		"message": "Add type definitions for apiService",
		"files": ["src/types/Repo.ts", "package.json", "tests/components.test.ts"]
	},
	{
		"sha": "a5d3c3b7",
		"authored_at": "2024-02-01T11:31:00.000Z",
		"message": "Remove deprecated Tooltip",
		"files": ["vite.config.ts", "src/hooks/useAuth.ts"]
	},
	{
		"sha": "080fe10e",
		"authored_at": "2024-02-01T11:35:00.000Z",
		"message": "Refactor Timeline for clarity",
		"files": ["src/services/database.ts", "src/types/Commit.ts"]
	},
	{
		"sha": "7cc1ac28",
		"authored_at": "2024-02-01T11:42:00.000Z",
		"message": "Refactor SessionPanel for clarity",
		"files": [
			"tests/hooks.test.ts",
			"package.json",
			"vite.config.ts",
			"tests/utils.test.ts"
		]
	},
	{
		"sha": "bbf59465",
		"authored_at": "2024-02-01T11:46:00.000Z",
		"message": "Fix layout bug in useData",
		"files": ["package.json"]
	},
	{
		"sha": "918fe649",
		"authored_at": "2024-02-01T11:50:00.000Z",
		"message": "Refactor useData for clarity",
		"files": ["tests/services.test.ts"]
	},
	{
		"sha": "0d72ad01",
		"authored_at": "2024-02-01T11:57:00.000Z",
		"message": "Improve performance of SessionPanel",
		"files": ["vite.config.ts", "src/components/Modal.tsx"]
	},
	{
		"sha": "e325953c",
		"authored_at": "2024-02-01T12:02:00.000Z",
		"message": "Refactor useData for clarity",
		"files": [
			"README.md",
			"package.json",
			"src/components/Modal.tsx",
			"src/services/api.ts",
			"vite.config.ts"
		]
	},
	{
		"sha": "5e8c7fe3",
		"authored_at": "2024-02-01T12:05:00.000Z",
		"message": "Improve performance of Button",
		"files": ["package.json"]
	},
	{
		"sha": "39c14cbb",
		"authored_at": "2024-02-01T12:12:00.000Z",
		"message": "Update SessionPanel to use new API",
		"files": ["README.md", "tests/services.test.ts", "src/hooks/useBadge.ts"]
	},
	{
		"sha": "e74e95b4",
		"authored_at": "2024-02-01T12:16:00.000Z",
		"message": "Refactor SessionPanel for clarity",
		"files": ["package.json", "src/hooks/useBadge.ts", "src/types/Repo.ts"]
	},
	{
		"sha": "ac000594",
		"authored_at": "2024-02-01T12:21:00.000Z",
		"message": "Fix type error in SessionPanel",
		"files": [
			"tests/utils.test.ts",
			"package.json",
			"src/components/Input.tsx",
			"README.md"
		]
	},
	{
		"sha": "d9912f64",
		"authored_at": "2024-02-01T12:26:00.000Z",
		"message": "Update apiService to use new API",
		"files": [
			"src/types/Commit.ts",
			"vite.config.ts",
			"README.md",
			"tests/services.test.ts",
			"package.json"
		]
	},
	{
		"sha": "4cc8696f",
		"authored_at": "2024-02-01T12:31:00.000Z",
		"message": "Add type definitions for Timeline",
		"files": [
			"README.md",
			"src/types/Commit.ts",
			"src/types/Link.ts",
			"src/components/Badge.tsx"
		]
	},
	{
		"sha": "62dda318",
		"authored_at": "2024-02-01T12:37:00.000Z",
		"message": "Improve performance of apiService",
		"files": ["vite.config.ts", "src/utils/format.ts"]
	},
	{
		"sha": "e27cfe5f",
		"authored_at": "2024-02-01T12:41:00.000Z",
		"message": "Add tests for SessionPanel",
		"files": [
			"src/components/Input.tsx",
			"tests/utils.test.ts",
			"vite.config.ts",
			"src/types/Session.ts"
		]
	},
	{
		"sha": "7b14dff7",
		"authored_at": "2024-02-01T12:47:00.000Z",
		"message": "Refactor useData for clarity",
		"files": ["tests/integration.test.ts"]
	},
	{
		"sha": "b2da9ed3",
		"authored_at": "2024-02-01T12:50:00.000Z",
		"message": "Fix layout bug in useData",
		"files": ["src/services/database.ts", "src/components/Modal.tsx"]
	},
	{
		"sha": "f0099c4d",
		"authored_at": "2024-02-01T12:56:00.000Z",
		"message": "Remove deprecated Panel",
		"files": [
			"src/services/auth.ts",
			"README.md",
			"src/services/api.ts",
			"tests/services.test.ts"
		]
	},
	{
		"sha": "486a490d",
		"authored_at": "2024-02-01T13:00:00.000Z",
		"message": "Fix type error in Button",
		"files": [
			"src/types/Session.ts",
			"src/types/User.ts",
			"package.json",
			"src/components/Input.tsx"
		]
	},
	{
		"sha": "a084006f",
		"authored_at": "2024-02-01T13:05:00.000Z",
		"message": "Add type definitions for SessionPanel",
		"files": ["src/types/Session.ts"]
	},
	{
		"sha": "39676879",
		"authored_at": "2024-02-01T13:11:00.000Z",
		"message": "Remove deprecated Modal",
		"files": [
			"src/hooks/useData.ts",
			"vite.config.ts",
			"README.md",
			"src/hooks/useModal.ts",
			"tests/integration.test.ts"
		]
	},
	{
		"sha": "1821743f",
		"authored_at": "2024-02-01T13:16:00.000Z",
		"message": "Add tests for Timeline",
		"files": [
			"vite.config.ts",
			"src/utils/validate.ts",
			"src/utils/format.ts",
			"src/hooks/useData.ts",
			"src/services/storage.ts"
		]
	},
	{
		"sha": "4bb16928",
		"authored_at": "2024-02-01T13:22:00.000Z",
		"message": "Add type definitions for Timeline",
		"files": [
			"vite.config.ts",
			"src/services/storage.ts",
			"src/utils/transform.ts",
			"src/types/Session.ts"
		]
	},
	{
		"sha": "c4f01051",
		"authored_at": "2024-02-01T13:27:00.000Z",
		"message": "Refactor useData for clarity",
		"files": [
			"src/hooks/useModal.ts",
			"src/components/Input.tsx",
			"src/components/Badge.tsx"
		]
	},
	{
		"sha": "9e28bf14",
		"authored_at": "2024-02-01T13:30:00.000Z",
		"message": "Fix type error in Button",
		"files": ["src/components/Button.tsx"]
	},
	{
		"sha": "18f71cae",
		"authored_at": "2024-02-01T13:36:00.000Z",
		"message": "Add Panel component",
		"files": [
			"README.md",
			"src/hooks/useBadge.ts",
			"src/utils/compute.ts",
			"src/types/Link.ts"
		]
	},
	{
		"sha": "96c56136",
		"authored_at": "2024-02-01T13:42:00.000Z",
		"message": "Remove deprecated Badge",
		"files": [
			"src/utils/transform.ts",
			"vite.config.ts",
			"README.md",
			"src/hooks/useForm.ts"
		]
	},
	{
		"sha": "40fed04b",
		"authored_at": "2024-02-01T13:46:00.000Z",
		"message": "Improve performance of Timeline",
		"files": [
			"vite.config.ts",
			"src/utils/parse.ts",
			"README.md",
			"src/types/Commit.ts",
			"package.json"
		]
	},
	{
		"sha": "293d806b",
		"authored_at": "2024-02-01T13:50:00.000Z",
		"message": "Add tests for apiService",
		"files": [
			"vite.config.ts",
			"src/components/Badge.tsx",
			"src/hooks/useData.ts",
			"src/components/Button.tsx",
			"package.json"
		]
	},
	{
		"sha": "86ca1d87",
		"authored_at": "2024-02-01T13:55:00.000Z",
		"message": "Refactor Button for clarity",
		"files": [
			"src/types/Commit.ts",
			"README.md",
			"src/types/Repo.ts",
			"vite.config.ts"
		]
	},
	{
		"sha": "c39f339e",
		"authored_at": "2024-02-01T14:02:00.000Z",
		"message": "Improve performance of useData",
		"files": [
			"README.md",
			"src/types/Session.ts",
			"src/components/Modal.tsx",
			"package.json",
			"vite.config.ts"
		]
	},
	{
		"sha": "3a6805b9",
		"authored_at": "2024-02-01T14:07:00.000Z",
		"message": "Add Panel component",
		"files": [
			"README.md",
			"src/utils/format.ts",
			"tests/components.test.ts",
			"src/services/api.ts",
			"src/types/Session.ts"
		]
	},
	{
		"sha": "841212bc",
		"authored_at": "2024-02-01T14:10:00.000Z",
		"message": "Add type definitions for Timeline",
		"files": [
			"src/services/storage.ts",
			"src/hooks/useData.ts",
			"tests/utils.test.ts",
			"src/hooks/useModal.ts",
			"src/utils/format.ts"
		]
	},
	{
		"sha": "ad71f871",
		"authored_at": "2024-02-01T14:15:00.000Z",
		"message": "Remove deprecated Dialog",
		"files": [
			"vite.config.ts",
			"README.md",
			"package.json",
			"src/services/auth.ts",
			"src/types/Commit.ts"
		]
	},
	{
		"sha": "4a23958f",
		"authored_at": "2024-02-01T14:22:00.000Z",
		"message": "Add Badge component",
		"files": ["vite.config.ts", "src/utils/validate.ts"]
	},
	{
		"sha": "54c3c2e8",
		"authored_at": "2024-02-01T14:27:00.000Z",
		"message": "Add type definitions for Button",
		"files": ["README.md"]
	},
	{
		"sha": "678c6c06",
		"authored_at": "2024-02-01T14:32:00.000Z",
		"message": "Add type definitions for useData",
		"files": [
			"src/utils/validate.ts",
			"tests/integration.test.ts",
			"src/hooks/useModal.ts"
		]
	},
	{
		"sha": "d2aef929",
		"authored_at": "2024-02-01T14:36:00.000Z",
		"message": "Add type definitions for Button",
		"files": ["src/components/Button.tsx"]
	},
	{
		"sha": "448b478c",
		"authored_at": "2024-02-01T14:41:00.000Z",
		"message": "Add type definitions for useData",
		"files": [
			"tests/components.test.ts",
			"src/components/Button.tsx",
			"src/types/Repo.ts"
		]
	},
	{
		"sha": "99c1a6f3",
		"authored_at": "2024-02-01T14:47:00.000Z",
		"message": "Fix accessibility issue in useData",
		"files": [
			"vite.config.ts",
			"src/services/api.ts",
			"src/utils/parse.ts",
			"tests/services.test.ts",
			"src/hooks/useAuth.ts"
		]
	},
	{
		"sha": "c2f5884a",
		"authored_at": "2024-02-01T14:50:00.000Z",
		"message": "Add Tooltip component",
		"files": ["vite.config.ts", "package.json"]
	},
	{
		"sha": "bb037c08",
		"authored_at": "2024-02-01T14:57:00.000Z",
		"message": "Fix type error in Timeline",
		"files": [
			"vite.config.ts",
			"src/types/Link.ts",
			"src/components/Dialog.tsx",
			"src/types/Repo.ts",
			"src/hooks/useBadge.ts"
		]
	},
	{
		"sha": "a0191de8",
		"authored_at": "2024-02-01T15:01:00.000Z",
		"message": "Add type definitions for Timeline",
		"files": [
			"package.json",
			"tests/hooks.test.ts",
			"src/utils/compute.ts",
			"src/hooks/useForm.ts",
			"vite.config.ts"
		]
	},
	{
		"sha": "ad5d5176",
		"authored_at": "2024-02-01T15:06:00.000Z",
		"message": "Add tests for SessionPanel",
		"files": [
			"src/types/Repo.ts",
			"src/services/cache.ts",
			"src/services/auth.ts",
			"src/hooks/useAuth.ts",
			"tests/utils.test.ts"
		]
	},
	{
		"sha": "24734a70",
		"authored_at": "2024-02-01T15:10:00.000Z",
		"message": "Add Badge component",
		"files": [
			"src/hooks/useModal.ts",
			"src/hooks/useAuth.ts",
			"src/components/Dialog.tsx",
			"src/components/Input.tsx",
			"src/utils/transform.ts"
		]
	},
	{
		"sha": "1fd9b109",
		"authored_at": "2024-02-01T15:15:00.000Z",
		"message": "Refactor Button for clarity",
		"files": [
			"src/types/Commit.ts",
			"package.json",
			"src/hooks/useAuth.ts",
			"src/hooks/useModal.ts",
			"src/utils/compute.ts"
		]
	},
	{
		"sha": "63acc163",
		"authored_at": "2024-02-01T15:20:00.000Z",
		"message": "Improve performance of useData",
		"files": [
			"src/utils/format.ts",
			"src/hooks/useData.ts",
			"src/types/Link.ts"
		]
	},
	{
		"sha": "a869254f",
		"authored_at": "2024-02-01T15:27:00.000Z",
		"message": "Add Panel component",
		"files": ["README.md", "src/utils/transform.ts", "tests/hooks.test.ts"]
	},
	{
		"sha": "c51c400c",
		"authored_at": "2024-02-01T15:32:00.000Z",
		"message": "Remove deprecated Dialog",
		"files": ["vite.config.ts", "src/hooks/useModal.ts"]
	},
	{
		"sha": "d6d6a5b1",
		"authored_at": "2024-02-01T15:35:00.000Z",
		"message": "Improve performance of Timeline",
		"files": [
			"src/components/Button.tsx",
			"vite.config.ts",
			"README.md",
			"src/hooks/useBadge.ts"
		]
	},
	{
		"sha": "085d6a6e",
		"authored_at": "2024-02-01T15:41:00.000Z",
		"message": "Refactor useData for clarity",
		"files": [
			"src/services/api.ts",
			"README.md",
			"src/components/Modal.tsx",
			"tests/integration.test.ts"
		]
	},
	{
		"sha": "b30ed14e",
		"authored_at": "2024-02-01T15:45:00.000Z",
		"message": "Fix layout bug in apiService",
		"files": ["README.md", "src/hooks/useAuth.ts", "vite.config.ts"]
	},
	{
		"sha": "1406c24d",
		"authored_at": "2024-02-01T15:52:00.000Z",
		"message": "Add Badge component",
		"files": ["src/hooks/useAuth.ts", "vite.config.ts"]
	},
	{
		"sha": "add38f74",
		"authored_at": "2024-02-01T15:55:00.000Z",
		"message": "Add type definitions for useData",
		"files": ["src/types/Commit.ts"]
	},
	{
		"sha": "1686dfc2",
		"authored_at": "2024-02-01T16:02:00.000Z",
		"message": "Add tests for Timeline",
		"files": ["vite.config.ts", "src/utils/transform.ts"]
	},
	{
		"sha": "b28a4d9b",
		"authored_at": "2024-02-01T16:07:00.000Z",
		"message": "Add Modal component",
		"files": [
			"src/services/api.ts",
			"src/services/storage.ts",
			"src/utils/transform.ts",
			"src/components/Dialog.tsx",
			"src/hooks/useData.ts"
		]
	},
	{
		"sha": "cb85fe42",
		"authored_at": "2024-02-01T16:10:00.000Z",
		"message": "Fix layout bug in Timeline",
		"files": ["src/components/Button.tsx"]
	},
	{
		"sha": "98d1e3d4",
		"authored_at": "2024-02-01T16:17:00.000Z",
		"message": "Update SessionPanel to use new API",
		"files": [
			"tests/hooks.test.ts",
			"README.md",
			"package.json",
			"src/types/Repo.ts",
			"src/hooks/useForm.ts"
		]
	},
	{
		"sha": "bb332508",
		"authored_at": "2024-02-01T16:20:00.000Z",
		"message": "Refactor useData for clarity",
		"files": ["tests/services.test.ts", "package.json", "vite.config.ts"]
	},
	{
		"sha": "874afeaa",
		"authored_at": "2024-02-01T16:25:00.000Z",
		"message": "Refactor SessionPanel for clarity",
		"files": ["package.json", "src/services/cache.ts"]
	},
	{
		"sha": "83f5efcc",
		"authored_at": "2024-02-01T16:30:00.000Z",
		"message": "Add tests for SessionPanel",
		"files": [
			"src/types/Link.ts",
			"vite.config.ts",
			"README.md",
			"package.json",
			"src/services/storage.ts"
		]
	},
	{
		"sha": "87e99b2f",
		"authored_at": "2024-02-01T16:37:00.000Z",
		"message": "Update apiService to use new API",
		"files": [
			"vite.config.ts",
			"src/components/Input.tsx",
			"src/components/Button.tsx",
			"tests/hooks.test.ts",
			"src/services/storage.ts"
		]
	},
	{
		"sha": "6def66c4",
		"authored_at": "2024-02-01T16:40:00.000Z",
		"message": "Refactor Timeline for clarity",
		"files": [
			"vite.config.ts",
			"src/components/Modal.tsx",
			"README.md",
			"src/utils/format.ts"
		]
	},
	{
		"sha": "dfb01121",
		"authored_at": "2024-02-01T16:47:00.000Z",
		"message": "Refactor Button for clarity",
		"files": [
			"package.json",
			"src/hooks/useBadge.ts",
			"src/components/Badge.tsx"
		]
	},
	{
		"sha": "0398bd68",
		"authored_at": "2024-02-01T16:51:00.000Z",
		"message": "Refactor apiService for clarity",
		"files": [
			"README.md",
			"vite.config.ts",
			"tests/services.test.ts",
			"src/components/Modal.tsx",
			"src/types/Link.ts"
		]
	},
	{
		"sha": "4b4b1a89",
		"authored_at": "2024-02-01T16:55:00.000Z",
		"message": "Improve performance of useData",
		"files": ["package.json", "vite.config.ts"]
	},
	{
		"sha": "d4bd73e9",
		"authored_at": "2024-02-01T17:02:00.000Z",
		"message": "Add Dialog component",
		"files": [
			"vite.config.ts",
			"package.json",
			"tests/components.test.ts",
			"src/components/Modal.tsx"
		]
	},
	{
		"sha": "1889f4ca",
		"authored_at": "2024-02-01T17:05:00.000Z",
		"message": "Add tests for apiService",
		"files": ["tests/hooks.test.ts"]
	},
	{
		"sha": "ca8acd60",
		"authored_at": "2024-02-01T17:12:00.000Z",
		"message": "Add Tooltip component",
		"files": [
			"src/components/Button.tsx",
			"README.md",
			"src/types/Repo.ts",
			"src/services/auth.ts",
			"src/services/database.ts"
		]
	},
	{
		"sha": "200c2d39",
		"authored_at": "2024-02-01T17:16:00.000Z",
		"message": "Remove deprecated Panel",
		"files": ["src/services/database.ts"]
	},
	{
		"sha": "d350adcf",
		"authored_at": "2024-02-01T17:22:00.000Z",
		"message": "Add Modal component",
		"files": ["vite.config.ts"]
	},
	{
		"sha": "7bab265c",
		"authored_at": "2024-02-01T17:25:00.000Z",
		"message": "Add type definitions for Timeline",
		"files": [
			"src/utils/transform.ts",
			"package.json",
			"src/components/Badge.tsx"
		]
	},
	{
		"sha": "2d23593a",
		"authored_at": "2024-02-01T17:32:00.000Z",
		"message": "Remove deprecated Panel",
		"files": ["src/hooks/useBadge.ts"]
	},
	{
		"sha": "80249320",
		"authored_at": "2024-02-01T17:37:00.000Z",
		"message": "Add type definitions for Button",
		"files": [
			"src/utils/format.ts",
			"src/services/cache.ts",
			"src/types/User.ts",
			"package.json",
			"README.md"
		]
	},
	{
		"sha": "1950eb78",
		"authored_at": "2024-02-01T17:40:00.000Z",
		"message": "Refactor Button for clarity",
		"files": ["package.json"]
	},
	{
		"sha": "4125f90a",
		"authored_at": "2024-02-01T17:45:00.000Z",
		"message": "Add tests for useData",
		"files": [
			"src/types/Commit.ts",
			"src/types/Repo.ts",
			"src/utils/parse.ts",
			"vite.config.ts"
		]
	},
	{
		"sha": "a1788429",
		"authored_at": "2024-02-01T17:50:00.000Z",
		"message": "Update Timeline to use new API",
		"files": ["src/utils/format.ts"]
	},
	{
		"sha": "45882fa0",
		"authored_at": "2024-02-01T17:57:00.000Z",
		"message": "Fix layout bug in useData",
		"files": ["package.json", "tests/hooks.test.ts", "src/services/api.ts"]
	},
	{
		"sha": "8495a186",
		"authored_at": "2024-02-01T18:00:00.000Z",
		"message": "Add tests for SessionPanel",
		"files": [
			"src/services/cache.ts",
			"src/components/Modal.tsx",
			"src/utils/compute.ts"
		]
	},
	{
		"sha": "b07684c5",
		"authored_at": "2024-02-01T18:05:00.000Z",
		"message": "Add type definitions for SessionPanel",
		"files": ["src/services/database.ts"]
	},
	{
		"sha": "416a39f5",
		"authored_at": "2024-02-01T18:10:00.000Z",
		"message": "Add Tooltip component",
		"files": [
			"README.md",
			"src/types/Session.ts",
			"tests/hooks.test.ts",
			"src/types/Repo.ts"
		]
	},
	{
		"sha": "518d0481",
		"authored_at": "2024-02-01T18:16:00.000Z",
		"message": "Add Panel component",
		"files": ["vite.config.ts", "package.json", "src/components/Badge.tsx"]
	},
	{
		"sha": "d2dddf4e",
		"authored_at": "2024-02-01T18:20:00.000Z",
		"message": "Improve performance of Button",
		"files": ["tests/services.test.ts"]
	},
	{
		"sha": "f324b441",
		"authored_at": "2024-02-01T18:27:00.000Z",
		"message": "Add tests for apiService",
		"files": [
			"src/hooks/useData.ts",
			"src/utils/transform.ts",
			"src/components/Input.tsx"
		]
	},
	{
		"sha": "033e7a9a",
		"authored_at": "2024-02-01T18:30:00.000Z",
		"message": "Improve performance of Timeline",
		"files": [
			"src/utils/transform.ts",
			"src/components/Dialog.tsx",
			"tests/hooks.test.ts",
			"tests/services.test.ts",
			"src/types/Link.ts"
		]
	},
	{
		"sha": "80838dc4",
		"authored_at": "2024-02-01T18:36:00.000Z",
		"message": "Improve performance of Button",
		"files": ["package.json", "vite.config.ts", "src/utils/compute.ts"]
	},
	{
		"sha": "3ddcf160",
		"authored_at": "2024-02-01T18:42:00.000Z",
		"message": "Add tests for SessionPanel",
		"files": [
			"vite.config.ts",
			"src/utils/format.ts",
			"src/hooks/useModal.ts",
			"src/hooks/useForm.ts"
		]
	},
	{
		"sha": "ad1f525d",
		"authored_at": "2024-02-01T18:45:00.000Z",
		"message": "Add tests for useData",
		"files": ["src/components/Badge.tsx"]
	},
	{
		"sha": "b6322be5",
		"authored_at": "2024-02-01T18:50:00.000Z",
		"message": "Remove deprecated Tooltip",
		"files": ["src/hooks/useBadge.ts"]
	},
	{
		"sha": "92c2ddc7",
		"authored_at": "2024-02-01T18:55:00.000Z",
		"message": "Improve performance of apiService",
		"files": [
			"src/components/Dialog.tsx",
			"vite.config.ts",
			"tests/hooks.test.ts"
		]
	},
	{
		"sha": "62123b53",
		"authored_at": "2024-02-01T19:00:00.000Z",
		"message": "Fix race condition in useData",
		"files": ["src/utils/validate.ts", "package.json"]
	},
	{
		"sha": "d51d00b6",
		"authored_at": "2024-02-01T19:05:00.000Z",
		"message": "Remove deprecated Modal",
		"files": [
			"package.json",
			"tests/services.test.ts",
			"src/components/Input.tsx"
		]
	},
	{
		"sha": "595769c9",
		"authored_at": "2024-02-01T19:12:00.000Z",
		"message": "Add Tooltip component",
		"files": [
			"README.md",
			"src/components/Dialog.tsx",
			"tests/utils.test.ts",
			"src/components/Badge.tsx",
			"vite.config.ts"
		]
	},
	{
		"sha": "3ff1f63a",
		"authored_at": "2024-02-01T19:15:00.000Z",
		"message": "Remove deprecated Tooltip",
		"files": ["src/types/Link.ts", "README.md"]
	},
	{
		"sha": "36bf159a",
		"authored_at": "2024-02-01T19:20:00.000Z",
		"message": "Refactor Button for clarity",
		"files": ["src/hooks/useAuth.ts"]
	},
	{
		"sha": "ee2a1dd0",
		"authored_at": "2024-02-01T19:27:00.000Z",
		"message": "Fix type error in apiService",
		"files": [
			"vite.config.ts",
			"tests/components.test.ts",
			"tests/utils.test.ts"
		]
	},
	{
		"sha": "3a667123",
		"authored_at": "2024-02-01T19:30:00.000Z",
		"message": "Add Dialog component",
		"files": ["package.json", "README.md"]
	},
	{
		"sha": "1ff2309c",
		"authored_at": "2024-02-01T19:36:00.000Z",
		"message": "Fix layout bug in SessionPanel",
		"files": ["src/utils/compute.ts", "src/hooks/useModal.ts"]
	},
	{
		"sha": "a380e53e",
		"authored_at": "2024-02-01T19:40:00.000Z",
		"message": "Update apiService to use new API",
		"files": ["package.json", "src/components/Input.tsx", "src/types/User.ts"]
	},
	{
		"sha": "ae530cad",
		"authored_at": "2024-02-01T19:47:00.000Z",
		"message": "Fix memory leak in Timeline",
		"files": ["README.md", "src/utils/transform.ts"]
	},
	{
		"sha": "dbc652fe",
		"authored_at": "2024-02-01T19:51:00.000Z",
		"message": "Update SessionPanel to use new API",
		"files": ["package.json"]
	},
	{
		"sha": "441c0f6b",
		"authored_at": "2024-02-01T19:55:00.000Z",
		"message": "Add type definitions for SessionPanel",
		"files": ["src/components/Input.tsx", "src/components/Badge.tsx"]
	},
	{
		"sha": "a2226378",
		"authored_at": "2024-02-01T20:00:00.000Z",
		"message": "Add type definitions for Timeline",
		"files": ["src/utils/compute.ts"]
	},
	{
		"sha": "58130853",
		"authored_at": "2024-02-01T20:05:00.000Z",
		"message": "Add Panel component",
		"files": ["README.md"]
	},
	{
		"sha": "da51d2c9",
		"authored_at": "2024-02-01T20:11:00.000Z",
		"message": "Add tests for useData",
		"files": [
			"src/types/User.ts",
			"src/services/storage.ts",
			"src/services/auth.ts"
		]
	},
	{
		"sha": "79e0c818",
		"authored_at": "2024-02-01T20:15:00.000Z",
		"message": "Refactor useData for clarity",
		"files": [
			"src/types/Repo.ts",
			"src/utils/parse.ts",
			"src/utils/compute.ts",
			"tests/utils.test.ts",
			"README.md"
		]
	},
	{
		"sha": "746b0163",
		"authored_at": "2024-02-01T20:21:00.000Z",
		"message": "Add Panel component",
		"files": [
			"src/components/Input.tsx",
			"src/hooks/useData.ts",
			"src/types/Commit.ts",
			"src/utils/parse.ts",
			"src/services/api.ts"
		]
	},
	{
		"sha": "4782be3e",
		"authored_at": "2024-02-01T20:26:00.000Z",
		"message": "Update Button to use new API",
		"files": [
			"src/services/storage.ts",
			"src/services/cache.ts",
			"tests/integration.test.ts"
		]
	},
	{
		"sha": "ad0f89c2",
		"authored_at": "2024-02-01T20:31:00.000Z",
		"message": "Remove deprecated Dialog",
		"files": [
			"src/utils/parse.ts",
			"src/types/Commit.ts",
			"vite.config.ts",
			"src/services/storage.ts"
		]
	},
	{
		"sha": "1ee2fd1f",
		"authored_at": "2024-02-01T20:35:00.000Z",
		"message": "Refactor useData for clarity",
		"files": ["vite.config.ts", "README.md", "src/components/Badge.tsx"]
	},
	{
		"sha": "2f4e1c7e",
		"authored_at": "2024-02-01T20:41:00.000Z",
		"message": "Add Modal component",
		"files": [
			"src/utils/format.ts",
			"src/components/Badge.tsx",
			"package.json",
			"src/components/Modal.tsx"
		]
	},
	{
		"sha": "2f5152dc",
		"authored_at": "2024-02-01T20:45:00.000Z",
		"message": "Fix layout bug in apiService",
		"files": ["src/hooks/useData.ts", "src/types/User.ts"]
	},
	{
		"sha": "2cdbad6c",
		"authored_at": "2024-02-01T20:50:00.000Z",
		"message": "Add Badge component",
		"files": ["package.json", "src/components/Input.tsx"]
	},
	{
		"sha": "12a0afef",
		"authored_at": "2024-02-01T20:56:00.000Z",
		"message": "Improve performance of Button",
		"files": [
			"src/services/storage.ts",
			"README.md",
			"src/services/cache.ts",
			"src/hooks/useAuth.ts"
		]
	},
	{
		"sha": "e9aa515e",
		"authored_at": "2024-02-01T21:02:00.000Z",
		"message": "Add type definitions for Timeline",
		"files": [
			"src/utils/validate.ts",
			"src/types/Commit.ts",
			"src/services/api.ts"
		]
	},
	{
		"sha": "17aedde8",
		"authored_at": "2024-02-01T21:05:00.000Z",
		"message": "Add Panel component",
		"files": ["src/services/api.ts", "src/types/User.ts", "tests/hooks.test.ts"]
	},
	{
		"sha": "4816aa56",
		"authored_at": "2024-02-01T21:11:00.000Z",
		"message": "Refactor Button for clarity",
		"files": [
			"vite.config.ts",
			"src/utils/parse.ts",
			"README.md",
			"src/types/Commit.ts"
		]
	},
	{
		"sha": "e9305d17",
		"authored_at": "2024-02-01T21:16:00.000Z",
		"message": "Improve performance of useData",
		"files": [
			"src/types/Commit.ts",
			"src/utils/transform.ts",
			"src/components/Modal.tsx"
		]
	},
	{
		"sha": "a892d4b7",
		"authored_at": "2024-02-01T21:21:00.000Z",
		"message": "Add type definitions for useData",
		"files": ["src/services/api.ts", "package.json"]
	},
	{
		"sha": "a287a56e",
		"authored_at": "2024-02-01T21:27:00.000Z",
		"message": "Fix race condition in SessionPanel",
		"files": [
			"tests/components.test.ts",
			"package.json",
			"src/hooks/useForm.ts",
			"vite.config.ts"
		]
	},
	{
		"sha": "18f5dcae",
		"authored_at": "2024-02-01T21:31:00.000Z",
		"message": "Add Panel component",
		"files": ["README.md"]
	},
	{
		"sha": "2372ee5a",
		"authored_at": "2024-02-01T21:36:00.000Z",
		"message": "Add type definitions for useData",
		"files": ["package.json"]
	},
	{
		"sha": "9c60f578",
		"authored_at": "2024-02-01T21:40:00.000Z",
		"message": "Update apiService to use new API",
		"files": [
			"src/utils/parse.ts",
			"src/utils/transform.ts",
			"src/components/Badge.tsx"
		]
	},
	{
		"sha": "bb79822b",
		"authored_at": "2024-02-01T21:45:00.000Z",
		"message": "Update useData to use new API",
		"files": ["vite.config.ts"]
	},
	{
		"sha": "7b37fed7",
		"authored_at": "2024-02-01T21:51:00.000Z",
		"message": "Add tests for Timeline",
		"files": [
			"package.json",
			"src/services/storage.ts",
			"src/components/Input.tsx",
			"src/types/Session.ts"
		]
	},
	{
		"sha": "20716e55",
		"authored_at": "2024-02-01T21:57:00.000Z",
		"message": "Remove deprecated Panel",
		"files": ["src/components/Dialog.tsx", "src/utils/format.ts"]
	},
	{
		"sha": "63e0e262",
		"authored_at": "2024-02-01T22:01:00.000Z",
		"message": "Update Timeline to use new API",
		"files": ["src/types/Link.ts", "src/types/Session.ts"]
	},
	{
		"sha": "6b622ee2",
		"authored_at": "2024-02-01T22:06:00.000Z",
		"message": "Add Dialog component",
		"files": [
			"src/types/User.ts",
			"src/components/Modal.tsx",
			"tests/components.test.ts"
		]
	},
	{
		"sha": "ce098fca",
		"authored_at": "2024-02-01T22:11:00.000Z",
		"message": "Update SessionPanel to use new API",
		"files": [
			"src/components/Badge.tsx",
			"vite.config.ts",
			"README.md",
			"src/components/Button.tsx"
		]
	},
	{
		"sha": "be6ef66c",
		"authored_at": "2024-02-01T22:15:00.000Z",
		"message": "Fix accessibility issue in SessionPanel",
		"files": ["vite.config.ts", "src/types/User.ts", "src/services/storage.ts"]
	},
	{
		"sha": "00b0ceec",
		"authored_at": "2024-02-01T22:21:00.000Z",
		"message": "Update useData to use new API",
		"files": [
			"src/components/Button.tsx",
			"src/utils/parse.ts",
			"vite.config.ts",
			"src/hooks/useBadge.ts"
		]
	},
	{
		"sha": "61b22724",
		"authored_at": "2024-02-01T22:25:00.000Z",
		"message": "Improve performance of Timeline",
		"files": ["vite.config.ts", "src/utils/parse.ts"]
	},
	{
		"sha": "09a280ff",
		"authored_at": "2024-02-01T22:32:00.000Z",
		"message": "Add type definitions for useData",
		"files": [
			"src/utils/format.ts",
			"src/services/api.ts",
			"README.md",
			"package.json",
			"src/hooks/useAuth.ts"
		]
	},
	{
		"sha": "f424affa",
		"authored_at": "2024-02-01T22:35:00.000Z",
		"message": "Add Panel component",
		"files": ["src/services/database.ts", "package.json"]
	},
	{
		"sha": "ddd8aa0d",
		"authored_at": "2024-02-01T22:40:00.000Z",
		"message": "Add Modal component",
		"files": ["src/hooks/useModal.ts", "package.json", "tests/services.test.ts"]
	},
	{
		"sha": "e76c374d",
		"authored_at": "2024-02-01T22:45:00.000Z",
		"message": "Refactor apiService for clarity",
		"files": [
			"src/components/Button.tsx",
			"src/utils/transform.ts",
			"src/components/Dialog.tsx"
		]
	},
	{
		"sha": "2cc53819",
		"authored_at": "2024-02-01T22:51:00.000Z",
		"message": "Fix type error in apiService",
		"files": [
			"tests/hooks.test.ts",
			"src/components/Button.tsx",
			"src/utils/transform.ts",
			"tests/integration.test.ts"
		]
	},
	{
		"sha": "8d2dcbb1",
		"authored_at": "2024-02-01T22:57:00.000Z",
		"message": "Fix memory leak in SessionPanel",
		"files": [
			"src/types/Repo.ts",
			"src/components/Input.tsx",
			"src/components/Dialog.tsx"
		]
	},
	{
		"sha": "88e1794b",
		"authored_at": "2024-02-01T23:01:00.000Z",
		"message": "Add tests for apiService",
		"files": [
			"src/components/Badge.tsx",
			"vite.config.ts",
			"src/hooks/useForm.ts"
		]
	},
	{
		"sha": "0d61867d",
		"authored_at": "2024-02-01T23:07:00.000Z",
		"message": "Add tests for useData",
		"files": ["README.md", "src/hooks/useBadge.ts", "src/services/auth.ts"]
	},
	{
		"sha": "c218d28c",
		"authored_at": "2024-02-01T23:11:00.000Z",
		"message": "Add tests for Timeline",
		"files": ["package.json", "tests/hooks.test.ts", "src/services/cache.ts"]
	},
	{
		"sha": "02ef0c2b",
		"authored_at": "2024-02-01T23:17:00.000Z",
		"message": "Add type definitions for useData",
		"files": ["src/hooks/useAuth.ts", "src/types/User.ts"]
	},
	{
		"sha": "5d67f9e4",
		"authored_at": "2024-02-01T23:22:00.000Z",
		"message": "Add type definitions for Timeline",
		"files": [
			"tests/services.test.ts",
			"README.md",
			"src/utils/parse.ts",
			"src/components/Badge.tsx"
		]
	},
	{
		"sha": "8fb52aa1",
		"authored_at": "2024-02-01T23:27:00.000Z",
		"message": "Add Panel component",
		"files": ["src/components/Input.tsx", "README.md"]
	},
	{
		"sha": "c8449221",
		"authored_at": "2024-02-01T23:32:00.000Z",
		"message": "Improve performance of Button",
		"files": [
			"src/services/cache.ts",
			"src/utils/format.ts",
			"src/components/Dialog.tsx",
			"README.md"
		]
	},
	{
		"sha": "b87316a3",
		"authored_at": "2024-02-01T23:35:00.000Z",
		"message": "Add Badge component",
		"files": [
			"src/types/User.ts",
			"package.json",
			"README.md",
			"src/components/Button.tsx"
		]
	},
	{
		"sha": "bc4648e1",
		"authored_at": "2024-02-01T23:40:00.000Z",
		"message": "Add type definitions for Button",
		"files": ["src/services/auth.ts", "src/components/Modal.tsx"]
	},
	{
		"sha": "e706fdff",
		"authored_at": "2024-02-01T23:47:00.000Z",
		"message": "Refactor useData for clarity",
		"files": ["tests/utils.test.ts", "README.md", "src/hooks/useModal.ts"]
	},
	{
		"sha": "48cce955",
		"authored_at": "2024-02-01T23:50:00.000Z",
		"message": "Update apiService to use new API",
		"files": [
			"vite.config.ts",
			"src/utils/parse.ts",
			"tests/utils.test.ts",
			"src/hooks/useModal.ts"
		]
	},
	{
		"sha": "eab8b4e2",
		"authored_at": "2024-02-01T23:56:00.000Z",
		"message": "Add type definitions for SessionPanel",
		"files": [
			"tests/utils.test.ts",
			"src/utils/transform.ts",
			"package.json",
			"src/hooks/useForm.ts"
		]
	},
	{
		"sha": "255c9e97",
		"authored_at": "2024-02-02T00:00:00.000Z",
		"message": "Update Timeline to use new API",
		"files": ["src/components/Dialog.tsx", "src/utils/parse.ts"]
	},
	{
		"sha": "5ad6121e",
		"authored_at": "2024-02-02T00:06:00.000Z",
		"message": "Add Modal component",
		"files": ["README.md", "package.json"]
	},
	{
		"sha": "546ea209",
		"authored_at": "2024-02-02T00:12:00.000Z",
		"message": "Refactor Button for clarity",
		"files": ["src/components/Modal.tsx", "src/services/api.ts", "package.json"]
	},
	{
		"sha": "ad1925cc",
		"authored_at": "2024-02-02T00:17:00.000Z",
		"message": "Add type definitions for Button",
		"files": ["src/hooks/useModal.ts"]
	},
	{
		"sha": "d40350a0",
		"authored_at": "2024-02-02T00:20:00.000Z",
		"message": "Fix race condition in Timeline",
		"files": [
			"package.json",
			"src/hooks/useForm.ts",
			"src/services/database.ts",
			"tests/utils.test.ts",
			"src/types/User.ts"
		]
	},
	{
		"sha": "035b14b6",
		"authored_at": "2024-02-02T00:25:00.000Z",
		"message": "Add tests for apiService",
		"files": ["src/utils/validate.ts", "src/hooks/useData.ts"]
	},
	{
		"sha": "7b67d9f8",
		"authored_at": "2024-02-02T00:31:00.000Z",
		"message": "Fix accessibility issue in SessionPanel",
		"files": [
			"README.md",
			"src/hooks/useBadge.ts",
			"src/types/Link.ts",
			"tests/services.test.ts",
			"src/utils/format.ts"
		]
	},
	{
		"sha": "cb2efd0e",
		"authored_at": "2024-02-02T00:36:00.000Z",
		"message": "Update apiService to use new API",
		"files": ["src/types/Repo.ts"]
	},
	{
		"sha": "7c052c25",
		"authored_at": "2024-02-02T00:42:00.000Z",
		"message": "Refactor apiService for clarity",
		"files": [
			"src/types/Repo.ts",
			"package.json",
			"src/services/api.ts",
			"src/services/storage.ts"
		]
	},
	{
		"sha": "7a2041af",
		"authored_at": "2024-02-02T00:46:00.000Z",
		"message": "Remove deprecated Badge",
		"files": ["package.json"]
	},
	{
		"sha": "285d30b2",
		"authored_at": "2024-02-02T00:50:00.000Z",
		"message": "Add Modal component",
		"files": ["src/types/User.ts", "README.md", "src/components/Input.tsx"]
	},
	{
		"sha": "f06de170",
		"authored_at": "2024-02-02T00:57:00.000Z",
		"message": "Improve performance of apiService",
		"files": ["README.md", "src/services/database.ts"]
	},
	{
		"sha": "6fc674f8",
		"authored_at": "2024-02-02T01:00:00.000Z",
		"message": "Add tests for useData",
		"files": ["src/services/database.ts", "src/hooks/useModal.ts"]
	},
	{
		"sha": "0653e24d",
		"authored_at": "2024-02-02T01:07:00.000Z",
		"message": "Remove deprecated Dialog",
		"files": [
			"src/utils/parse.ts",
			"src/types/Repo.ts",
			"tests/integration.test.ts",
			"tests/hooks.test.ts",
			"src/hooks/useModal.ts"
		]
	},
	{
		"sha": "db8751f8",
		"authored_at": "2024-02-02T01:11:00.000Z",
		"message": "Remove deprecated Modal",
		"files": [
			"tests/hooks.test.ts",
			"src/components/Dialog.tsx",
			"package.json",
			"src/utils/compute.ts",
			"src/hooks/useAuth.ts"
		]
	},
	{
		"sha": "90d6dc21",
		"authored_at": "2024-02-02T01:17:00.000Z",
		"message": "Add type definitions for useData",
		"files": [
			"tests/integration.test.ts",
			"src/services/api.ts",
			"src/components/Badge.tsx",
			"tests/services.test.ts"
		]
	},
	{
		"sha": "dcefb669",
		"authored_at": "2024-02-02T01:20:00.000Z",
		"message": "Add Panel component",
		"files": [
			"package.json",
			"src/components/Badge.tsx",
			"vite.config.ts",
			"src/types/Repo.ts",
			"README.md"
		]
	},
	{
		"sha": "923f0392",
		"authored_at": "2024-02-02T01:27:00.000Z",
		"message": "Add tests for Button",
		"files": ["src/components/Button.tsx"]
	},
	{
		"sha": "e423d179",
		"authored_at": "2024-02-02T01:32:00.000Z",
		"message": "Refactor SessionPanel for clarity",
		"files": [
			"tests/hooks.test.ts",
			"src/hooks/useBadge.ts",
			"README.md",
			"src/hooks/useAuth.ts"
		]
	},
	{
		"sha": "6cbb67b8",
		"authored_at": "2024-02-02T01:37:00.000Z",
		"message": "Add tests for useData",
		"files": ["src/hooks/useModal.ts", "README.md", "src/services/cache.ts"]
	},
	{
		"sha": "c4f9b51d",
		"authored_at": "2024-02-02T01:40:00.000Z",
		"message": "Add tests for Button",
		"files": [
			"src/components/Modal.tsx",
			"README.md",
			"vite.config.ts",
			"src/types/Commit.ts"
		]
	},
	{
		"sha": "e6662271",
		"authored_at": "2024-02-02T01:45:00.000Z",
		"message": "Remove deprecated Dialog",
		"files": ["src/services/database.ts", "src/components/Modal.tsx"]
	},
	{
		"sha": "d377e789",
		"authored_at": "2024-02-02T01:50:00.000Z",
		"message": "Update Timeline to use new API",
		"files": ["package.json", "src/utils/compute.ts"]
	},
	{
		"sha": "a3b4cadd",
		"authored_at": "2024-02-02T01:56:00.000Z",
		"message": "Update Button to use new API",
		"files": ["src/hooks/useBadge.ts", "package.json"]
	},
	{
		"sha": "78b13ee1",
		"authored_at": "2024-02-02T02:02:00.000Z",
		"message": "Remove deprecated Tooltip",
		"files": [
			"README.md",
			"tests/integration.test.ts",
			"src/types/User.ts",
			"tests/components.test.ts",
			"package.json"
		]
	},
	{
		"sha": "fba7ab21",
		"authored_at": "2024-02-02T02:07:00.000Z",
		"message": "Improve performance of apiService",
		"files": [
			"src/types/Link.ts",
			"src/types/Session.ts",
			"tests/services.test.ts",
			"src/services/auth.ts",
			"vite.config.ts"
		]
	},
	{
		"sha": "eca96df2",
		"authored_at": "2024-02-02T02:12:00.000Z",
		"message": "Add Tooltip component",
		"files": [
			"src/services/api.ts",
			"package.json",
			"tests/integration.test.ts"
		]
	},
	{
		"sha": "128fdef9",
		"authored_at": "2024-02-02T02:16:00.000Z",
		"message": "Add Modal component",
		"files": [
			"README.md",
			"src/services/storage.ts",
			"src/components/Modal.tsx",
			"src/hooks/useForm.ts",
			"src/components/Badge.tsx"
		]
	},
	{
		"sha": "92a8bc06",
		"authored_at": "2024-02-02T02:20:00.000Z",
		"message": "Improve performance of SessionPanel",
		"files": ["package.json", "src/types/User.ts", "src/utils/transform.ts"]
	},
	{
		"sha": "958c3ec0",
		"authored_at": "2024-02-02T02:27:00.000Z",
		"message": "Add tests for Timeline",
		"files": ["src/components/Modal.tsx", "tests/hooks.test.ts", "package.json"]
	},
	{
		"sha": "07180b2f",
		"authored_at": "2024-02-02T02:30:00.000Z",
		"message": "Add type definitions for Timeline",
		"files": ["README.md"]
	},
	{
		"sha": "f31dd36c",
		"authored_at": "2024-02-02T02:36:00.000Z",
		"message": "Update apiService to use new API",
		"files": ["src/components/Button.tsx", "src/utils/compute.ts"]
	},
	{
		"sha": "61cebbc7",
		"authored_at": "2024-02-02T02:40:00.000Z",
		"message": "Remove deprecated Tooltip",
		"files": [
			"src/components/Dialog.tsx",
			"src/utils/validate.ts",
			"tests/utils.test.ts",
			"package.json"
		]
	},
	{
		"sha": "5b849ff7",
		"authored_at": "2024-02-02T02:45:00.000Z",
		"message": "Fix type error in Button",
		"files": [
			"src/components/Button.tsx",
			"README.md",
			"src/components/Dialog.tsx",
			"src/hooks/useData.ts"
		]
	},
	{
		"sha": "5edba717",
		"authored_at": "2024-02-02T02:50:00.000Z",
		"message": "Add Tooltip component",
		"files": [
			"src/types/Repo.ts",
			"src/utils/transform.ts",
			"tests/utils.test.ts",
			"README.md",
			"vite.config.ts"
		]
	},
	{
		"sha": "0faa200c",
		"authored_at": "2024-02-02T02:55:00.000Z",
		"message": "Add type definitions for Timeline",
		"files": ["vite.config.ts", "src/types/Session.ts"]
	},
	{
		"sha": "b6a1398a",
		"authored_at": "2024-02-02T03:01:00.000Z",
		"message": "Add tests for Button",
		"files": [
			"tests/utils.test.ts",
			"src/utils/format.ts",
			"src/components/Input.tsx",
			"src/types/Commit.ts",
			"vite.config.ts"
		]
	},
	{
		"sha": "67f54a94",
		"authored_at": "2024-02-02T03:06:00.000Z",
		"message": "Add Tooltip component",
		"files": [
			"vite.config.ts",
			"src/utils/parse.ts",
			"tests/services.test.ts",
			"README.md"
		]
	},
	{
		"sha": "411f4524",
		"authored_at": "2024-02-02T03:11:00.000Z",
		"message": "Refactor apiService for clarity",
		"files": ["src/hooks/useForm.ts", "src/services/cache.ts"]
	},
	{
		"sha": "ab159269",
		"authored_at": "2024-02-02T03:17:00.000Z",
		"message": "Improve performance of useData",
		"files": ["README.md", "package.json", "src/types/User.ts"]
	},
	{
		"sha": "5e49fc58",
		"authored_at": "2024-02-02T03:21:00.000Z",
		"message": "Add Modal component",
		"files": [
			"README.md",
			"package.json",
			"src/utils/compute.ts",
			"src/hooks/useAuth.ts"
		]
	},
	{
		"sha": "e17c85eb",
		"authored_at": "2024-02-02T03:25:00.000Z",
		"message": "Improve performance of Timeline",
		"files": [
			"vite.config.ts",
			"package.json",
			"src/utils/parse.ts",
			"src/utils/transform.ts"
		]
	},
	{
		"sha": "eefc64e8",
		"authored_at": "2024-02-02T03:30:00.000Z",
		"message": "Fix race condition in Timeline",
		"files": [
			"vite.config.ts",
			"src/utils/transform.ts",
			"src/hooks/useForm.ts",
			"README.md",
			"src/services/storage.ts"
		]
	},
	{
		"sha": "c3060fcf",
		"authored_at": "2024-02-02T03:35:00.000Z",
		"message": "Update Timeline to use new API",
		"files": ["vite.config.ts", "src/utils/parse.ts", "src/services/storage.ts"]
	},
	{
		"sha": "45b4bb51",
		"authored_at": "2024-02-02T03:40:00.000Z",
		"message": "Remove deprecated Tooltip",
		"files": [
			"src/services/cache.ts",
			"src/hooks/useData.ts",
			"src/hooks/useForm.ts"
		]
	},
	{
		"sha": "f466f9f4",
		"authored_at": "2024-02-02T03:45:00.000Z",
		"message": "Add Panel component",
		"files": ["vite.config.ts"]
	},
	{
		"sha": "69fa74bb",
		"authored_at": "2024-02-02T03:52:00.000Z",
		"message": "Refactor apiService for clarity",
		"files": [
			"src/utils/transform.ts",
			"src/hooks/useBadge.ts",
			"src/utils/compute.ts"
		]
	},
	{
		"sha": "810eb797",
		"authored_at": "2024-02-02T03:56:00.000Z",
		"message": "Add Badge component",
		"files": ["src/services/auth.ts", "vite.config.ts"]
	},
	{
		"sha": "c9f5eb6d",
		"authored_at": "2024-02-02T04:01:00.000Z",
		"message": "Add tests for apiService",
		"files": ["package.json"]
	},
	{
		"sha": "fee9e5bd",
		"authored_at": "2024-02-02T04:06:00.000Z",
		"message": "Refactor Timeline for clarity",
		"files": [
			"package.json",
			"README.md",
			"vite.config.ts",
			"src/types/Commit.ts"
		]
	},
	{
		"sha": "2abec331",
		"authored_at": "2024-02-02T04:11:00.000Z",
		"message": "Add type definitions for Timeline",
		"files": ["src/hooks/useBadge.ts"]
	},
	{
		"sha": "170c3ac0",
		"authored_at": "2024-02-02T04:16:00.000Z",
		"message": "Add type definitions for Timeline",
		"files": ["src/utils/format.ts", "package.json", "README.md"]
	},
	{
		"sha": "6aabe0b3",
		"authored_at": "2024-02-02T04:22:00.000Z",
		"message": "Add type definitions for Button",
		"files": ["vite.config.ts", "src/services/auth.ts", "README.md"]
	},
	{
		"sha": "66526fab",
		"authored_at": "2024-02-02T04:27:00.000Z",
		"message": "Add type definitions for Button",
		"files": [
			"src/hooks/useBadge.ts",
			"src/services/storage.ts",
			"src/utils/parse.ts",
			"vite.config.ts"
		]
	},
	{
		"sha": "0643e839",
		"authored_at": "2024-02-02T04:31:00.000Z",
		"message": "Update SessionPanel to use new API",
		"files": [
			"tests/integration.test.ts",
			"vite.config.ts",
			"src/hooks/useModal.ts",
			"package.json"
		]
	},
	{
		"sha": "cb20d8be",
		"authored_at": "2024-02-02T04:36:00.000Z",
		"message": "Add Modal component",
		"files": [
			"src/types/Session.ts",
			"src/types/Commit.ts",
			"package.json",
			"README.md",
			"src/components/Modal.tsx"
		]
	},
	{
		"sha": "ffb8f1bf",
		"authored_at": "2024-02-02T04:41:00.000Z",
		"message": "Refactor apiService for clarity",
		"files": ["package.json", "src/hooks/useForm.ts", "vite.config.ts"]
	},
	{
		"sha": "f0eec3e8",
		"authored_at": "2024-02-02T04:46:00.000Z",
		"message": "Add tests for SessionPanel",
		"files": ["tests/utils.test.ts"]
	},
	{
		"sha": "f9a260fb",
		"authored_at": "2024-02-02T04:50:00.000Z",
		"message": "Add Badge component",
		"files": [
			"src/utils/parse.ts",
			"package.json",
			"src/components/Dialog.tsx",
			"src/utils/compute.ts"
		]
	},
	{
		"sha": "2c613019",
		"authored_at": "2024-02-02T04:57:00.000Z",
		"message": "Improve performance of SessionPanel",
		"files": [
			"src/services/auth.ts",
			"package.json",
			"src/services/api.ts",
			"src/components/Button.tsx",
			"src/services/database.ts"
		]
	},
	{
		"sha": "9185be8c",
		"authored_at": "2024-02-02T05:00:00.000Z",
		"message": "Remove deprecated Dialog",
		"files": [
			"src/components/Modal.tsx",
			"tests/services.test.ts",
			"src/components/Button.tsx",
			"vite.config.ts"
		]
	},
	{
		"sha": "54488bfb",
		"authored_at": "2024-02-02T05:07:00.000Z",
		"message": "Improve performance of apiService",
		"files": [
			"src/components/Badge.tsx",
			"README.md",
			"package.json",
			"vite.config.ts",
			"src/components/Input.tsx"
		]
	},
	{
		"sha": "eaa54598",
		"authored_at": "2024-02-02T05:10:00.000Z",
		"message": "Improve performance of Button",
		"files": [
			"tests/services.test.ts",
			"src/services/database.ts",
			"tests/utils.test.ts",
			"src/types/Session.ts"
		]
	},
	{
		"sha": "c6c07496",
		"authored_at": "2024-02-02T05:16:00.000Z",
		"message": "Add Dialog component",
		"files": ["src/hooks/useForm.ts"]
	},
	{
		"sha": "76ffc04a",
		"authored_at": "2024-02-02T05:21:00.000Z",
		"message": "Fix type error in useData",
		"files": ["package.json", "src/services/api.ts", "src/types/User.ts"]
	},
	{
		"sha": "5dc0f9d3",
		"authored_at": "2024-02-02T05:25:00.000Z",
		"message": "Improve performance of Timeline",
		"files": ["src/utils/validate.ts"]
	},
	{
		"sha": "c9044679",
		"authored_at": "2024-02-02T05:31:00.000Z",
		"message": "Update useData to use new API",
		"files": [
			"src/components/Input.tsx",
			"src/hooks/useModal.ts",
			"src/hooks/useAuth.ts",
			"src/services/api.ts",
			"src/types/Commit.ts"
		]
	},
	{
		"sha": "a2576b0f",
		"authored_at": "2024-02-02T05:37:00.000Z",
		"message": "Add Panel component",
		"files": [
			"src/services/database.ts",
			"src/hooks/useForm.ts",
			"src/utils/format.ts"
		]
	},
	{
		"sha": "b8ef5bf1",
		"authored_at": "2024-02-02T05:42:00.000Z",
		"message": "Update apiService to use new API",
		"files": ["src/types/Commit.ts", "package.json"]
	},
	{
		"sha": "f9384285",
		"authored_at": "2024-02-02T05:46:00.000Z",
		"message": "Refactor SessionPanel for clarity",
		"files": [
			"package.json",
			"src/components/Badge.tsx",
			"vite.config.ts",
			"src/utils/transform.ts"
		]
	},
	{
		"sha": "df76e4a6",
		"authored_at": "2024-02-02T05:50:00.000Z",
		"message": "Add tests for Button",
		"files": [
			"tests/integration.test.ts",
			"README.md",
			"src/services/database.ts"
		]
	},
	{
		"sha": "3e5754a0",
		"authored_at": "2024-02-02T05:57:00.000Z",
		"message": "Add type definitions for Button",
		"files": [
			"src/utils/transform.ts",
			"src/services/database.ts",
			"src/types/Link.ts"
		]
	},
	{
		"sha": "31318185",
		"authored_at": "2024-02-02T06:01:00.000Z",
		"message": "Add tests for apiService",
		"files": [
			"src/utils/validate.ts",
			"vite.config.ts",
			"tests/hooks.test.ts",
			"src/utils/format.ts",
			"src/utils/compute.ts"
		]
	},
	{
		"sha": "253b9b9f",
		"authored_at": "2024-02-02T06:07:00.000Z",
		"message": "Fix race condition in apiService",
		"files": ["README.md"]
	},
	{
		"sha": "b320d77e",
		"authored_at": "2024-02-02T06:12:00.000Z",
		"message": "Improve performance of Button",
		"files": ["src/hooks/useBadge.ts"]
	},
	{
		"sha": "fd5d87bd",
		"authored_at": "2024-02-02T06:17:00.000Z",
		"message": "Add type definitions for apiService",
		"files": [
			"tests/services.test.ts",
			"README.md",
			"vite.config.ts",
			"src/services/storage.ts",
			"src/services/api.ts"
		]
	},
	{
		"sha": "7d97380e",
		"authored_at": "2024-02-02T06:20:00.000Z",
		"message": "Improve performance of Button",
		"files": [
			"README.md",
			"src/components/Modal.tsx",
			"src/utils/transform.ts",
			"src/utils/validate.ts",
			"src/components/Dialog.tsx"
		]
	},
	{
		"sha": "09f579a9",
		"authored_at": "2024-02-02T06:25:00.000Z",
		"message": "Refactor Timeline for clarity",
		"files": ["src/components/Modal.tsx", "src/components/Input.tsx"]
	},
	{
		"sha": "2166c3db",
		"authored_at": "2024-02-02T06:32:00.000Z",
		"message": "Remove deprecated Modal",
		"files": ["README.md"]
	},
	{
		"sha": "b2ae1bc0",
		"authored_at": "2024-02-02T06:35:00.000Z",
		"message": "Remove deprecated Panel",
		"files": [
			"tests/integration.test.ts",
			"src/components/Badge.tsx",
			"src/hooks/useBadge.ts"
		]
	},
	{
		"sha": "2e03c606",
		"authored_at": "2024-02-02T06:40:00.000Z",
		"message": "Fix race condition in Button",
		"files": [
			"tests/components.test.ts",
			"src/services/database.ts",
			"src/hooks/useAuth.ts"
		]
	},
	{
		"sha": "24bc6185",
		"authored_at": "2024-02-02T06:46:00.000Z",
		"message": "Add type definitions for SessionPanel",
		"files": ["src/services/cache.ts", "src/types/Session.ts"]
	},
	{
		"sha": "debeb3eb",
		"authored_at": "2024-02-02T06:51:00.000Z",
		"message": "Update SessionPanel to use new API",
		"files": ["vite.config.ts"]
	},
	{
		"sha": "8a0aa68c",
		"authored_at": "2024-02-02T06:56:00.000Z",
		"message": "Update Button to use new API",
		"files": [
			"package.json",
			"vite.config.ts",
			"src/services/auth.ts",
			"tests/integration.test.ts"
		]
	},
	{
		"sha": "fb335500",
		"authored_at": "2024-02-02T07:02:00.000Z",
		"message": "Update useData to use new API",
		"files": ["README.md", "vite.config.ts", "src/hooks/useForm.ts"]
	},
	{
		"sha": "245c0ece",
		"authored_at": "2024-02-02T07:06:00.000Z",
		"message": "Add tests for Timeline",
		"files": [
			"package.json",
			"tests/components.test.ts",
			"vite.config.ts",
			"src/services/database.ts",
			"src/services/cache.ts"
		]
	},
	{
		"sha": "0381bf9a",
		"authored_at": "2024-02-02T07:11:00.000Z",
		"message": "Refactor Timeline for clarity",
		"files": [
			"src/components/Button.tsx",
			"src/components/Input.tsx",
			"src/hooks/useBadge.ts",
			"src/services/auth.ts",
			"src/utils/parse.ts"
		]
	},
	{
		"sha": "a6b394a0",
		"authored_at": "2024-02-02T07:15:00.000Z",
		"message": "Remove deprecated Badge",
		"files": [
			"README.md",
			"src/utils/parse.ts",
			"src/utils/transform.ts",
			"tests/integration.test.ts",
			"src/hooks/useAuth.ts"
		]
	},
	{
		"sha": "83175858",
		"authored_at": "2024-02-02T07:22:00.000Z",
		"message": "Improve performance of apiService",
		"files": ["vite.config.ts", "src/hooks/useData.ts"]
	},
	{
		"sha": "c2a8e17c",
		"authored_at": "2024-02-02T07:25:00.000Z",
		"message": "Remove deprecated Tooltip",
		"files": ["vite.config.ts", "src/types/Commit.ts", "README.md"]
	},
	{
		"sha": "38006e4c",
		"authored_at": "2024-02-02T07:32:00.000Z",
		"message": "Refactor apiService for clarity",
		"files": ["src/components/Badge.tsx", "README.md", "src/services/cache.ts"]
	},
	{
		"sha": "de1ec023",
		"authored_at": "2024-02-02T07:37:00.000Z",
		"message": "Fix accessibility issue in apiService",
		"files": [
			"vite.config.ts",
			"tests/hooks.test.ts",
			"src/services/database.ts",
			"tests/utils.test.ts"
		]
	},
	{
		"sha": "5932f066",
		"authored_at": "2024-02-02T07:41:00.000Z",
		"message": "Improve performance of apiService",
		"files": [
			"src/utils/format.ts",
			"src/components/Modal.tsx",
			"src/utils/compute.ts",
			"src/types/Link.ts",
			"tests/integration.test.ts"
		]
	},
	{
		"sha": "b06b9081",
		"authored_at": "2024-02-02T07:47:00.000Z",
		"message": "Fix layout bug in SessionPanel",
		"files": ["package.json", "tests/utils.test.ts", "src/hooks/useForm.ts"]
	},
	{
		"sha": "4b6c3743",
		"authored_at": "2024-02-02T07:51:00.000Z",
		"message": "Fix memory leak in Button",
		"files": ["package.json", "src/types/User.ts"]
	},
	{
		"sha": "9ae11d9f",
		"authored_at": "2024-02-02T07:56:00.000Z",
		"message": "Fix layout bug in Button",
		"files": [
			"README.md",
			"src/components/Button.tsx",
			"tests/utils.test.ts",
			"src/components/Input.tsx",
			"src/utils/validate.ts"
		]
	},
	{
		"sha": "d6b24999",
		"authored_at": "2024-02-02T08:01:00.000Z",
		"message": "Update Timeline to use new API",
		"files": ["src/services/storage.ts"]
	},
	{
		"sha": "cf492547",
		"authored_at": "2024-02-02T08:05:00.000Z",
		"message": "Refactor useData for clarity",
		"files": ["README.md", "package.json", "src/types/User.ts"]
	},
	{
		"sha": "b1a395e4",
		"authored_at": "2024-02-02T08:12:00.000Z",
		"message": "Remove deprecated Badge",
		"files": [
			"src/types/Session.ts",
			"package.json",
			"tests/utils.test.ts",
			"src/components/Modal.tsx"
		]
	},
	{
		"sha": "09e66796",
		"authored_at": "2024-02-02T08:16:00.000Z",
		"message": "Add type definitions for Button",
		"files": [
			"src/utils/format.ts",
			"src/types/Repo.ts",
			"src/utils/parse.ts",
			"src/components/Modal.tsx",
			"src/types/Session.ts"
		]
	},
	{
		"sha": "60bf4efd",
		"authored_at": "2024-02-02T08:21:00.000Z",
		"message": "Add Panel component",
		"files": ["vite.config.ts"]
	},
	{
		"sha": "c0655feb",
		"authored_at": "2024-02-02T08:27:00.000Z",
		"message": "Add type definitions for useData",
		"files": [
			"src/types/User.ts",
			"src/types/Session.ts",
			"tests/integration.test.ts",
			"src/hooks/useBadge.ts",
			"src/services/api.ts"
		]
	},
	{
		"sha": "371f98c6",
		"authored_at": "2024-02-02T08:32:00.000Z",
		"message": "Remove deprecated Badge",
		"files": ["src/services/auth.ts", "tests/utils.test.ts"]
	},
	{
		"sha": "788e452c",
		"authored_at": "2024-02-02T08:35:00.000Z",
		"message": "Remove deprecated Modal",
		"files": ["package.json", "README.md", "src/services/database.ts"]
	},
	{
		"sha": "4b92eea8",
		"authored_at": "2024-02-02T08:41:00.000Z",
		"message": "Remove deprecated Badge",
		"files": ["tests/utils.test.ts"]
	},
	{
		"sha": "2dec17de",
		"authored_at": "2024-02-02T08:45:00.000Z",
		"message": "Remove deprecated Tooltip",
		"files": ["src/hooks/useForm.ts", "README.md", "src/utils/transform.ts"]
	},
	{
		"sha": "4076931a",
		"authored_at": "2024-02-02T08:50:00.000Z",
		"message": "Remove deprecated Modal",
		"files": ["tests/services.test.ts"]
	},
	{
		"sha": "57cb1a89",
		"authored_at": "2024-02-02T08:56:00.000Z",
		"message": "Improve performance of Button",
		"files": [
			"src/utils/validate.ts",
			"src/types/Session.ts",
			"package.json",
			"src/services/api.ts"
		]
	},
	{
		"sha": "e407e007",
		"authored_at": "2024-02-02T09:00:00.000Z",
		"message": "Fix memory leak in Timeline",
		"files": ["src/types/Session.ts"]
	},
	{
		"sha": "6f19a1b0",
		"authored_at": "2024-02-02T09:05:00.000Z",
		"message": "Add tests for useData",
		"files": [
			"src/services/database.ts",
			"src/services/storage.ts",
			"vite.config.ts",
			"src/types/Commit.ts"
		]
	},
	{
		"sha": "f4305fd6",
		"authored_at": "2024-02-02T09:10:00.000Z",
		"message": "Add tests for apiService",
		"files": [
			"src/components/Button.tsx",
			"src/services/auth.ts",
			"tests/utils.test.ts"
		]
	},
	{
		"sha": "72391d39",
		"authored_at": "2024-02-02T09:15:00.000Z",
		"message": "Update Button to use new API",
		"files": ["src/services/auth.ts"]
	},
	{
		"sha": "07fd44dd",
		"authored_at": "2024-02-02T09:22:00.000Z",
		"message": "Remove deprecated Panel",
		"files": ["src/hooks/useForm.ts", "vite.config.ts", "src/hooks/useData.ts"]
	},
	{
		"sha": "606b641f",
		"authored_at": "2024-02-02T09:26:00.000Z",
		"message": "Update apiService to use new API",
		"files": [
			"src/services/storage.ts",
			"src/components/Button.tsx",
			"tests/services.test.ts",
			"src/types/User.ts",
			"src/services/cache.ts"
		]
	},
	{
		"sha": "f96a322c",
		"authored_at": "2024-02-02T09:31:00.000Z",
		"message": "Add Tooltip component",
		"files": [
			"src/utils/transform.ts",
			"README.md",
			"vite.config.ts",
			"src/components/Input.tsx"
		]
	},
	{
		"sha": "dab70772",
		"authored_at": "2024-02-02T09:37:00.000Z",
		"message": "Add type definitions for apiService",
		"files": [
			"src/utils/validate.ts",
			"src/utils/parse.ts",
			"src/components/Badge.tsx"
		]
	},
	{
		"sha": "22bc9dd0",
		"authored_at": "2024-02-02T09:42:00.000Z",
		"message": "Improve performance of Timeline",
		"files": [
			"package.json",
			"tests/hooks.test.ts",
			"README.md",
			"src/hooks/useModal.ts"
		]
	},
	{
		"sha": "a957b5d3",
		"authored_at": "2024-02-02T09:45:00.000Z",
		"message": "Update useData to use new API",
		"files": ["tests/utils.test.ts", "src/components/Modal.tsx"]
	},
	{
		"sha": "23c118d8",
		"authored_at": "2024-02-02T09:51:00.000Z",
		"message": "Update useData to use new API",
		"files": ["src/hooks/useData.ts", "src/utils/parse.ts"]
	},
	{
		"sha": "fe02dc6a",
		"authored_at": "2024-02-02T09:57:00.000Z",
		"message": "Improve performance of apiService",
		"files": ["src/utils/parse.ts"]
	},
	{
		"sha": "f0ba974d",
		"authored_at": "2024-02-02T10:00:00.000Z",
		"message": "Add tests for SessionPanel",
		"files": ["src/utils/compute.ts", "vite.config.ts", "src/types/Link.ts"]
	},
	{
		"sha": "e403d740",
		"authored_at": "2024-02-02T10:06:00.000Z",
		"message": "Fix memory leak in SessionPanel",
		"files": [
			"src/services/database.ts",
			"vite.config.ts",
			"README.md",
			"src/hooks/useData.ts"
		]
	},
	{
		"sha": "5e416163",
		"authored_at": "2024-02-02T10:11:00.000Z",
		"message": "Improve performance of Button",
		"files": ["src/components/Modal.tsx"]
	},
	{
		"sha": "a4a321dc",
		"authored_at": "2024-02-02T10:17:00.000Z",
		"message": "Add tests for Button",
		"files": ["vite.config.ts"]
	},
	{
		"sha": "46936006",
		"authored_at": "2024-02-02T10:22:00.000Z",
		"message": "Remove deprecated Tooltip",
		"files": ["src/hooks/useAuth.ts"]
	},
	{
		"sha": "35a42ed8",
		"authored_at": "2024-02-02T10:25:00.000Z",
		"message": "Add type definitions for Button",
		"files": ["vite.config.ts", "README.md"]
	},
	{
		"sha": "e61e2f28",
		"authored_at": "2024-02-02T10:30:00.000Z",
		"message": "Remove deprecated Modal",
		"files": ["src/components/Modal.tsx", "README.md"]
	},
	{
		"sha": "e425350f",
		"authored_at": "2024-02-02T10:36:00.000Z",
		"message": "Remove deprecated Dialog",
		"files": ["src/types/User.ts", "src/types/Commit.ts", "README.md"]
	},
	{
		"sha": "bd39bfdf",
		"authored_at": "2024-02-02T10:41:00.000Z",
		"message": "Refactor useData for clarity",
		"files": [
			"README.md",
			"tests/utils.test.ts",
			"src/services/cache.ts",
			"src/types/Repo.ts"
		]
	},
	{
		"sha": "3f0591d0",
		"authored_at": "2024-02-02T10:47:00.000Z",
		"message": "Add type definitions for Button",
		"files": ["src/types/Session.ts", "tests/components.test.ts"]
	},
	{
		"sha": "06b38e03",
		"authored_at": "2024-02-02T10:51:00.000Z",
		"message": "Fix type error in apiService",
		"files": [
			"src/components/Badge.tsx",
			"src/hooks/useForm.ts",
			"src/services/storage.ts",
			"src/utils/transform.ts"
		]
	},
	{
		"sha": "cf008587",
		"authored_at": "2024-02-02T10:57:00.000Z",
		"message": "Add Badge component",
		"files": [
			"package.json",
			"vite.config.ts",
			"src/utils/parse.ts",
			"src/services/storage.ts",
			"src/types/User.ts"
		]
	},
	{
		"sha": "02da0bc6",
		"authored_at": "2024-02-02T11:00:00.000Z",
		"message": "Add type definitions for useData",
		"files": ["vite.config.ts", "src/utils/validate.ts", "src/types/Session.ts"]
	},
	{
		"sha": "21300443",
		"authored_at": "2024-02-02T11:06:00.000Z",
		"message": "Refactor Button for clarity",
		"files": ["src/types/User.ts"]
	},
	{
		"sha": "ce9296f7",
		"authored_at": "2024-02-02T11:12:00.000Z",
		"message": "Add type definitions for Button",
		"files": [
			"src/services/storage.ts",
			"README.md",
			"src/types/Link.ts",
			"src/hooks/useData.ts",
			"vite.config.ts"
		]
	},
	{
		"sha": "6967d799",
		"authored_at": "2024-02-02T11:15:00.000Z",
		"message": "Add type definitions for Timeline",
		"files": [
			"src/utils/validate.ts",
			"src/components/Input.tsx",
			"vite.config.ts"
		]
	},
	{
		"sha": "f360c06a",
		"authored_at": "2024-02-02T11:20:00.000Z",
		"message": "Add tests for apiService",
		"files": [
			"src/utils/transform.ts",
			"src/services/auth.ts",
			"tests/services.test.ts",
			"src/services/storage.ts"
		]
	},
	{
		"sha": "7e109c26",
		"authored_at": "2024-02-02T11:26:00.000Z",
		"message": "Add tests for SessionPanel",
		"files": ["src/utils/validate.ts"]
	},
	{
		"sha": "ed291bbc",
		"authored_at": "2024-02-02T11:31:00.000Z",
		"message": "Remove deprecated Tooltip",
		"files": ["src/components/Input.tsx", "README.md"]
	},
	{
		"sha": "4840e733",
		"authored_at": "2024-02-02T11:35:00.000Z",
		"message": "Add Panel component",
		"files": [
			"src/hooks/useForm.ts",
			"src/utils/parse.ts",
			"vite.config.ts",
			"README.md"
		]
	},
	{
		"sha": "c0837b67",
		"authored_at": "2024-02-02T11:42:00.000Z",
		"message": "Improve performance of SessionPanel",
		"files": [
			"tests/utils.test.ts",
			"src/hooks/useData.ts",
			"package.json",
			"README.md"
		]
	},
	{
		"sha": "5aec9a29",
		"authored_at": "2024-02-02T11:46:00.000Z",
		"message": "Add tests for SessionPanel",
		"files": ["README.md", "src/services/storage.ts"]
	},
	{
		"sha": "51e09a98",
		"authored_at": "2024-02-02T11:52:00.000Z",
		"message": "Improve performance of apiService",
		"files": ["src/hooks/useData.ts"]
	},
	{
		"sha": "14d7702a",
		"authored_at": "2024-02-02T11:55:00.000Z",
		"message": "Refactor SessionPanel for clarity",
		"files": ["src/components/Badge.tsx", "README.md", "package.json"]
	},
	{
		"sha": "106ecc8b",
		"authored_at": "2024-02-02T12:01:00.000Z",
		"message": "Fix race condition in Button",
		"files": ["src/components/Dialog.tsx", "src/types/Session.ts"]
	},
	{
		"sha": "d3c89e84",
		"authored_at": "2024-02-02T12:05:00.000Z",
		"message": "Refactor apiService for clarity",
		"files": [
			"src/types/Commit.ts",
			"README.md",
			"src/types/User.ts",
			"src/components/Input.tsx",
			"src/utils/validate.ts"
		]
	},
	{
		"sha": "3e91c211",
		"authored_at": "2024-02-02T12:11:00.000Z",
		"message": "Update Button to use new API",
		"files": [
			"src/hooks/useAuth.ts",
			"src/utils/format.ts",
			"src/utils/validate.ts"
		]
	},
	{
		"sha": "fff41f79",
		"authored_at": "2024-02-02T12:16:00.000Z",
		"message": "Update Timeline to use new API",
		"files": ["src/services/cache.ts", "package.json"]
	},
	{
		"sha": "d82d7dc6",
		"authored_at": "2024-02-02T12:22:00.000Z",
		"message": "Update SessionPanel to use new API",
		"files": [
			"vite.config.ts",
			"tests/hooks.test.ts",
			"tests/services.test.ts",
			"src/utils/compute.ts"
		]
	},
	{
		"sha": "51c8bc61",
		"authored_at": "2024-02-02T12:26:00.000Z",
		"message": "Add type definitions for SessionPanel",
		"files": [
			"src/hooks/useBadge.ts",
			"tests/components.test.ts",
			"src/types/User.ts"
		]
	},
	{
		"sha": "b03c90ee",
		"authored_at": "2024-02-02T12:31:00.000Z",
		"message": "Fix accessibility issue in useData",
		"files": [
			"tests/hooks.test.ts",
			"src/components/Input.tsx",
			"src/services/api.ts"
		]
	},
	{
		"sha": "da205f03",
		"authored_at": "2024-02-02T12:37:00.000Z",
		"message": "Refactor Timeline for clarity",
		"files": ["src/services/storage.ts", "src/utils/validate.ts"]
	},
	{
		"sha": "5403cb3d",
		"authored_at": "2024-02-02T12:41:00.000Z",
		"message": "Update apiService to use new API",
		"files": ["src/utils/compute.ts", "README.md"]
	},
	{
		"sha": "096bb61f",
		"authored_at": "2024-02-02T12:47:00.000Z",
		"message": "Fix layout bug in SessionPanel",
		"files": ["src/types/User.ts", "src/services/auth.ts"]
	},
	{
		"sha": "082a677b",
		"authored_at": "2024-02-02T12:52:00.000Z",
		"message": "Refactor useData for clarity",
		"files": ["src/components/Button.tsx", "src/types/Session.ts"]
	},
	{
		"sha": "a043103f",
		"authored_at": "2024-02-02T12:56:00.000Z",
		"message": "Add type definitions for Button",
		"files": ["src/types/Commit.ts"]
	},
	{
		"sha": "561e8c33",
		"authored_at": "2024-02-02T13:02:00.000Z",
		"message": "Update apiService to use new API",
		"files": [
			"tests/utils.test.ts",
			"tests/services.test.ts",
			"tests/integration.test.ts"
		]
	},
	{
		"sha": "f2f0b458",
		"authored_at": "2024-02-02T13:07:00.000Z",
		"message": "Add type definitions for Button",
		"files": [
			"README.md",
			"src/utils/validate.ts",
			"src/services/database.ts",
			"tests/integration.test.ts"
		]
	},
	{
		"sha": "8c8df8eb",
		"authored_at": "2024-02-02T13:10:00.000Z",
		"message": "Fix accessibility issue in useData",
		"files": ["src/hooks/useData.ts"]
	},
	{
		"sha": "dc71a313",
		"authored_at": "2024-02-02T13:16:00.000Z",
		"message": "Add tests for SessionPanel",
		"files": ["README.md", "src/components/Dialog.tsx"]
	},
	{
		"sha": "7657f75b",
		"authored_at": "2024-02-02T13:20:00.000Z",
		"message": "Update Timeline to use new API",
		"files": ["src/hooks/useData.ts", "vite.config.ts"]
	},
	{
		"sha": "7896b9a0",
		"authored_at": "2024-02-02T13:26:00.000Z",
		"message": "Update SessionPanel to use new API",
		"files": ["README.md", "tests/components.test.ts"]
	},
	{
		"sha": "87f297f0",
		"authored_at": "2024-02-02T13:31:00.000Z",
		"message": "Add tests for useData",
		"files": [
			"src/services/cache.ts",
			"src/services/storage.ts",
			"package.json"
		]
	},
	{
		"sha": "483becb3",
		"authored_at": "2024-02-02T13:35:00.000Z",
		"message": "Improve performance of Timeline",
		"files": [
			"src/services/auth.ts",
			"README.md",
			"src/hooks/useModal.ts",
			"src/types/Repo.ts"
		]
	},
	{
		"sha": "e1838b6e",
		"authored_at": "2024-02-02T13:42:00.000Z",
		"message": "Remove deprecated Tooltip",
		"files": ["vite.config.ts"]
	},
	{
		"sha": "bb671237",
		"authored_at": "2024-02-02T13:46:00.000Z",
		"message": "Update Button to use new API",
		"files": ["tests/services.test.ts"]
	},
	{
		"sha": "b0d8b3ae",
		"authored_at": "2024-02-02T13:51:00.000Z",
		"message": "Fix race condition in Button",
		"files": [
			"src/hooks/useBadge.ts",
			"src/services/storage.ts",
			"src/hooks/useForm.ts",
			"src/services/database.ts"
		]
	},
	{
		"sha": "0c83db45",
		"authored_at": "2024-02-02T13:57:00.000Z",
		"message": "Update Timeline to use new API",
		"files": ["src/hooks/useAuth.ts"]
	},
	{
		"sha": "6d2b79fb",
		"authored_at": "2024-02-02T14:02:00.000Z",
		"message": "Add type definitions for apiService",
		"files": ["src/hooks/useBadge.ts"]
	},
	{
		"sha": "16e2a433",
		"authored_at": "2024-02-02T14:06:00.000Z",
		"message": "Remove deprecated Modal",
		"files": [
			"README.md",
			"src/types/User.ts",
			"src/hooks/useForm.ts",
			"tests/services.test.ts"
		]
	},
	{
		"sha": "a08f244e",
		"authored_at": "2024-02-02T14:12:00.000Z",
		"message": "Fix memory leak in Timeline",
		"files": ["src/hooks/useForm.ts", "src/services/database.ts"]
	},
	{
		"sha": "427b8cf2",
		"authored_at": "2024-02-02T14:16:00.000Z",
		"message": "Add Badge component",
		"files": [
			"tests/hooks.test.ts",
			"src/services/database.ts",
			"src/services/storage.ts",
			"src/components/Modal.tsx"
		]
	},
	{
		"sha": "c77cb45d",
		"authored_at": "2024-02-02T14:21:00.000Z",
		"message": "Add Badge component",
		"files": [
			"src/hooks/useAuth.ts",
			"src/services/storage.ts",
			"src/types/Session.ts",
			"src/hooks/useData.ts"
		]
	},
	{
		"sha": "c34ac086",
		"authored_at": "2024-02-02T14:26:00.000Z",
		"message": "Improve performance of useData",
		"files": [
			"src/components/Button.tsx",
			"src/services/cache.ts",
			"vite.config.ts",
			"tests/utils.test.ts",
			"src/hooks/useBadge.ts"
		]
	},
	{
		"sha": "c2bded74",
		"authored_at": "2024-02-02T14:30:00.000Z",
		"message": "Add tests for SessionPanel",
		"files": ["README.md", "package.json"]
	},
	{
		"sha": "126813f7",
		"authored_at": "2024-02-02T14:35:00.000Z",
		"message": "Add type definitions for Timeline",
		"files": ["package.json", "src/services/storage.ts"]
	},
	{
		"sha": "8a56cedf",
		"authored_at": "2024-02-02T14:41:00.000Z",
		"message": "Add tests for Timeline",
		"files": ["src/hooks/useBadge.ts", "src/components/Badge.tsx"]
	},
	{
		"sha": "4de5ec47",
		"authored_at": "2024-02-02T14:45:00.000Z",
		"message": "Improve performance of Timeline",
		"files": [
			"src/utils/validate.ts",
			"src/components/Input.tsx",
			"README.md",
			"tests/integration.test.ts"
		]
	},
	{
		"sha": "4fe1d558",
		"authored_at": "2024-02-02T14:51:00.000Z",
		"message": "Add type definitions for Timeline",
		"files": [
			"vite.config.ts",
			"tests/utils.test.ts",
			"src/types/Link.ts",
			"src/hooks/useAuth.ts"
		]
	},
	{
		"sha": "6d3765cc",
		"authored_at": "2024-02-02T14:56:00.000Z",
		"message": "Add tests for apiService",
		"files": [
			"tests/hooks.test.ts",
			"src/hooks/useAuth.ts",
			"vite.config.ts",
			"src/hooks/useForm.ts"
		]
	},
	{
		"sha": "87ee43b2",
		"authored_at": "2024-02-02T15:02:00.000Z",
		"message": "Remove deprecated Dialog",
		"files": ["package.json", "vite.config.ts"]
	},
	{
		"sha": "9302f178",
		"authored_at": "2024-02-02T15:05:00.000Z",
		"message": "Add tests for SessionPanel",
		"files": ["README.md", "src/services/database.ts"]
	}
]
